pzfx_parser.py
pzfx_parser-0.4.dist-info/LICENSE
pzfx_parser-0.4.dist-info/WHEEL
pzfx_parser-0.4.dist-info/METADATA
pzfx_parser-0.4.dist-info/RECORD
