Metadata-Version: 2.1
Name: pzfx_parser
Version: 0.4
Summary: Package to load and parse tables in a Prism pzfx file.
Home-page: https://github.com/ulido/pzfx_parser
Author: Ulrich Dobramysl
Author-email: ulrich.dobramysl@gmail.com
Classifier: License :: OSI Approved :: MIT License
Requires-Dist: numpy
Requires-Dist: pandas
